changedetector/__init__.py
changedetector/detectchange.py
changedetector/gobals_variables.py
changedetector/makeParser.py
changedetector/menu.py
changedetector/versionControl.py
changedetector/wrapperComponents.py
changedetector/wrm.py
changedetector/wro.py
changedetector/wrs.py
changedetector/wtch.py
changedetector/scripts/detectchange.fish
changedetector/scripts/detectchange.sh
changedetector-0.6.4.dist-info/METADATA
changedetector-0.6.4.dist-info/WHEEL
changedetector-0.6.4.dist-info/entry_points.txt
changedetector-0.6.4.dist-info/licenses/LICENCE
changedetector-0.6.4.dist-info/RECORD
